{
  "ScenarioVerifier0.1.0": 1704908315,
  "ScenarioVerifierFactory0.1.0": 1704908320,
  "VerifierSigWrapper0.1.0": 1704908328,
  "CredentialAtomicQuerySigValidator0.1.0": 1704908342,
  "NexeraVerifierEntrypoint0.1.0": 1704908347,
  "VerifierEntrypointFactory0.1.0": 1704908351,
  "ProxyAavePool0.1.0": 1704908396,
  "SimpleWhitelist0.1.0": 1704908400,
  "ExampleGatedNFTMinterV00.1.0": 1707730520,
  "ExampleGatedNFTMinter0.1.0": 1707730524,
  "ExampleGatedNFTMinter0.1.1": 1708095252,
  "ExampleNFTMinter0.1.0": 1708525084,
  "ExampleGatedNFTMinter0.1.2": 1708532609,
  "ExampleGatedNFTMinter0.1.3": 1710172856,
  "ExampleGatedNFTMinterUpgradeable0.1.1": 1710172872,
  "ExampleMultipleInputs0.1.0": 1710172877,
  "ExampleGatedNFTMinter0.1.4": 1710346009
}